pygifconv_thj/__init__.py
pygifconv_thj/converter.py
pygifconv_thj-1.0.0.dist-info/LICENSE
pygifconv_thj-1.0.0.dist-info/METADATA
pygifconv_thj-1.0.0.dist-info/WHEEL
pygifconv_thj-1.0.0.dist-info/top_level.txt
pygifconv_thj-1.0.0.dist-info/RECORD
